{
  "type": "note",
  "content": "\u003cblockquote\u003e\r\nWe walk through a full day in the life of an ordinary English peasant during the Middle Ages. Based entirely on real historical records, not fantasy tropes and a bit of speculation. From sunrise in the fields to meals, family life, work, and rest, discover how tough, busy, and surprisingly organised their days really were. You'll learn: What time peasants woke up (and why it wasn’t always dawn), What they actually ate (hint: not just bread and gruel). The jobs men, women, and children did.\u003cbr\u003e\r\nWhether you're into medieval history, building immersive fantasy worlds, or just curious about how different life used to be, this video offers a grounded, eye-opening look at the real medieval experience.\r\n\u003c/blockquote\u003e\r\n\u003cp\u003e\u003ca href=\"https://www.youtube.com/watch?v=LRwwXxhXdHU\u0026ab_channel=ModernHistoryTV\"\u003eWhat did MEDIEVAL PEASANTS do all day?\u003c/a\u003e\u003c/p\u003e\r\n\u003cfigure\u003e\u003cimg src=\"https://img.youtube.com/vi/LRwwXxhXdHU/maxresdefault.jpg\" alt=\"Video thumbnail\" class=\"u-photo\"\u003e\u003c/figure\u003e",
  "publishedAt": "2025-05-19T00:16:39.0960937+02:00",
  "slug": "2025/334e87330a0f3a4f14974cde820d24f6",
  "permalink": "/notes/334e87330a0f3a4f14974cde820d24f6",
  "tags": [
    "Medieval",
    "History",
    "Video"
  ]
}