{
    "type": "note",
    "markdown": "Added a 👍️ Thumbs Up button to all my (content) pages. Got the idea from Bearblog.\r\n\r\nIt's meant for people who interact with my content from my site, but don't have their own #IndieWeb setup.\r\n\r\n\u003cimg src=\"/kd/images/notes/2025/screenshot_ack.png\" class=\"u-photo\" alt=\"Screenshot of Thumbs Up button with text 'Just wanna leave an acknowledgment? Use this anonymous thumbs up button.'\"\u003e",
    "publishedAt": "2025-11-12T13:54:53.785136+01:00",
    "slug": "2025/8f5533455431310f072e2ee1c4b1377e",
    "permalink": "/notes/8f5533455431310f072e2ee1c4b1377e",
    "tags": [
        "IndieWeb"
    ]
}