{
    "type": "note",
    "markdown": "Now that the core of my content management system is done, it's so easy to add features that sound expensive, like markdown support and opengraph fetching.\r\n\r\nBut they were relatively easy to do (thanks to open source library support) and add so much to my site! 😃",
    "publishedAt": "2024-12-15T21:08:51.9455982+01:00",
    "slug": "b1bbe09b52de3d3cfb06354e3e3dcec9",
    "permalink": "/notes/b1bbe09b52de3d3cfb06354e3e3dcec9",
    "tags": [
        "OpenSource",
        "IndieWeb",
        "Markdown",
        "OpenGraph"
    ]
}