{
    "type": "photo",
    "title": "Flags in Sønderborg",
    "publishedAt": "2013-07-14T14:07:10Z",
    "content": "/kd/photos/flickr/flags-in-snderborg_9386926071_o.jpg",
    "slug": "3958a65d1fd4bc5a3a264765d8fea09f",
    "permalink": "/photos/3958a65d1fd4bc5a3a264765d8fea09f",
    "author": {
        "name": "Gerben Jacobs",
        "url": "https://gerben.dev",
        "photo": "https://gerben.dev/images/avatar.jpg"
    },
    "syndication": [
        {
            "type": "flickr",
            "url": "https://www.flickr.com/photos/theonewithout/9386926071/"
        }
    ]
}