{
    "type": "photo",
    "title": "Løkken",
    "publishedAt": "2013-07-16T12:26:09Z",
    "content": "/kd/photos/flickr/lkken_9389686144_o.jpg",
    "slug": "72eab46b4d5c7911ccb2aaafec82008b",
    "permalink": "/photos/72eab46b4d5c7911ccb2aaafec82008b",
    "author": {
        "name": "Gerben Jacobs",
        "url": "https://gerben.dev",
        "photo": "https://gerben.dev/images/avatar.jpg"
    },
    "syndication": [
        {
            "type": "flickr",
            "url": "https://www.flickr.com/photos/theonewithout/9389686144/"
        }
    ]
}