{
    "type": "photo",
    "title": "Church in Stavanger",
    "publishedAt": "2013-07-18T15:07:11Z",
    "content": "/kd/photos/flickr/church-in-stavanger_9389977833_o.jpg",
    "slug": "ab5620891ae6795bb0f8763d38c2eee4",
    "permalink": "/photos/ab5620891ae6795bb0f8763d38c2eee4",
    "author": {
        "name": "Gerben Jacobs",
        "url": "https://gerben.dev",
        "photo": "https://gerben.dev/images/avatar.jpg"
    },
    "syndication": [
        {
            "type": "flickr",
            "url": "https://www.flickr.com/photos/theonewithout/9389977833/"
        }
    ]
}